tests/__init__.py
tests/test_cli.py
tests/test_decoder.py
tests/test_encoder.py
tests/test_tokon_basic.py
tests/test_tokon_comprehensive.py
tests/test_tokon_schema.py
tokon/__init__.py
tokon/cli.py
tokon/compact.py
tokon/decoder.py
tokon/encoder.py
tokon/exceptions.py
tokon/schema.py
tokon/streaming.py
tokon/validator.py
tokon-1.1.0.dist-info/licenses/LICENSE
tokon-1.1.0.dist-info/METADATA
tokon-1.1.0.dist-info/WHEEL
tokon-1.1.0.dist-info/entry_points.txt
tokon-1.1.0.dist-info/top_level.txt
tokon-1.1.0.dist-info/RECORD
